setup.py
tractdb/__init__.py
tractdb.egg-info/PKG-INFO
tractdb.egg-info/SOURCES.txt
tractdb.egg-info/dependency_links.txt
tractdb.egg-info/entry_points.txt
tractdb.egg-info/not-zip-safe
tractdb.egg-info/requires.txt
tractdb.egg-info/top_level.txt
tractdb/client/__init__.py
tractdb/client/accounts.py
tractdb/client/client.py
tractdb/client/documents.py
tractdb/client/roles.py
tractdb/server/__init__.py
tractdb/server/accounts.py
tractdb/server/documents.py