Metadata-Version: 1.0
Name: tractdb
Version: 0.1.14
Summary: TractDB
Home-page: https://tractdb.org
Author: UNKNOWN
Author-email: UNKNOWN
License: UNKNOWN
Platform: UNKNOWN
